Cars/Audi.py
Cars/Bmw.py
Cars/Nissan.py
Cars/__init__.py
speedy_cars/__init__.py
speedy_cars/Cars/Audi.py
speedy_cars/Cars/Bmw.py
speedy_cars/Cars/Nissan.py
speedy_cars/Cars/__init__.py
speedy_cars/F1s/Mercedez.py
speedy_cars/F1s/__init__.py
speedy_cars-2024.1.2.dist-info/LICENSE.txt
speedy_cars-2024.1.2.dist-info/METADATA
speedy_cars-2024.1.2.dist-info/WHEEL
speedy_cars-2024.1.2.dist-info/entry_points.txt
speedy_cars-2024.1.2.dist-info/top_level.txt
speedy_cars-2024.1.2.dist-info/RECORD
