Metadata-Version: 2.1
Name: speedy-cars
Version: 2024.1.2
Summary: Lovely Spam! Wonderful Spam!
Home-page: https://github.com/pypa/sampleproject
Author: Another person
Author-email: Pradyun Gedam <pradyun@example.com>, Tzu-Ping Chung <tzu-ping@example.com>, different.person@example.com
Maintainer-email: Brett Cannon <brett@example.com>
Project-URL: Homepage, https://example.com
Project-URL: Documentation, https://readthedocs.org
Project-URL: Repository, https://github.com/me/spam.git
Project-URL: Issues, https://github.com/me/spam/issues
Project-URL: Changelog, https://github.com/me/spam/blob/master/CHANGELOG.md
Project-URL: DOWNLOAD, https://example.com/abc.tar.gz
Keywords: speedy,cars
Classifier: Development Status :: 4 - Beta
Classifier: Programming Language :: Python
Requires-Python: >=3.7, <4
License-File: LICENSE.txt
